setup.py
django_routers.egg-info/PKG-INFO
django_routers.egg-info/SOURCES.txt
django_routers.egg-info/dependency_links.txt
django_routers.egg-info/top_level.txt
routers/__init__.py
routers/router.py
routers/settings.py