Metadata-Version: 1.1
Name: django-routers
Version: 0.2
Summary: Django multiple databases, auto routers
Home-page: https://github.com/avelino/django-routers/
Author: Thiago Avelino
Author-email: thiagoavelinoster@gmail.com
License: BSD
Download-URL: https://github.com/avelino/django-routers/tarball/master
Keywords: django apps routers multi db
Platform: UNKNOWN
Classifier: Environment :: Plugins
Classifier: Framework :: Django
Classifier: Intended Audience :: Developers
Classifier: License :: OSI Approved :: BSD License
Classifier: Operating System :: OS Independent
Classifier: Programming Language :: Python
Classifier: Topic :: Software Development :: Libraries :: Python Modules
